{
    "17379390963331367437": {
        "guid": "17379390963331367437",
        "name": "Janos Hammerknuckle",
        "level": 5,
        "attackable": 0,
        "vendor": 1,
        "target": "0",
        "hp": 102,
        "x": -8909.46,
        "y": -104.163,
        "z": 82.0314
    },
    "17379391162342703625": {
        "guid": "17379391162342703625",
        "name": "Merissa Stilwell",
        "level": 5,
        "attackable": 0,
        "vendor": 0,
        "target": "0",
        "hp": 102,
        "x": -8908.31,
        "y": -108.521,
        "z": 81.9314
    },
    "17379390975830393346": {
        "guid": "17379390975830393346",
        "name": "Deputy Willem",
        "level": 18,
        "attackable": 0,
        "vendor": 0,
        "target": "0",
        "hp": 417,
        "x": -8947.64,
        "y": -132.319,
        "z": 83.7199
    },
    "17379391052670042627": {
        "guid": "17379391052670042627",
        "name": "Riding White Stallion",
        "level": 1,
        "attackable": 0,
        "vendor": 0,
        "target": "0",
        "hp": 42,
        "x": -8933.85,
        "y": -166.93,
        "z": 81.0317
    },
    "17379390967039132158": {
        "guid": "17379390967039132158",
        "name": "Diseased Young Wolf",
        "level": 1,
        "attackable": 1,
        "vendor": 0,
        "target": "0",
        "hp": 42,
        "x": -9007.31,
        "y": -128.173,
        "z": 84.1516
    },
    "17379390967039132165": {
        "guid": "17379390967039132165",
        "name": "Diseased Young Wolf",
        "level": 1,
        "attackable": 1,
        "vendor": 0,
        "target": "0",
        "hp": 42,
        "x": -8987.4,
        "y": -149.859,
        "z": 81.5799
    },
    "17379390967039132157": {
        "guid": "17379390967039132157",
        "name": "Diseased Young Wolf",
        "level": 1,
        "attackable": 1,
        "vendor": 0,
        "target": "0",
        "hp": 42,
        "x": -8949.66,
        "y": -85.3181,
        "z": 87.6976
    },
    "17379390967039132156": {
        "guid": "17379390967039132156",
        "name": "Diseased Young Wolf",
        "level": 1,
        "attackable": 1,
        "vendor": 0,
        "target": "0",
        "hp": 42,
        "x": -8973.84,
        "y": -81.3831,
        "z": 87.0507
    },
    "17379390963180372501": {
        "guid": "17379390963180372501",
        "name": "Diseased Timber Wolf",
        "level": 2,
        "attackable": 1,
        "vendor": 0,
        "target": "0",
        "hp": 55,
        "x": -8988,
        "y": -170.724,
        "z": 78.1475
    },
    "17379390989570933256": {
        "guid": "17379390989570933256",
        "name": "Northshire Guard",
        "level": 65,
        "attackable": 0,
        "vendor": 0,
        "target": "0",
        "hp": 11828,
        "x": -8998.91,
        "y": -85.8362,
        "z": 85.8759
    },
    "17379390967039132368": {
        "guid": "17379390967039132368",
        "name": "Diseased Young Wolf",
        "level": 1,
        "attackable": 1,
        "vendor": 0,
        "target": "0",
        "hp": 42,
        "x": -8987.04,
        "y": -173.009,
        "z": 77.7838
    }
}